<?xml version="1.0" encoding="utf-8"?>
<edmx:Edmx Version="4.0" xmlns:edmx="http://docs.oasis-open.org/odata/ns/edmx">
    <edmx:Reference Uri="../../catalogservice;v=2/Vocabularies(TechnicalName='%2FIWBEP%2FVOC_COMMON',Version='0001',SAP__Origin='')/$value">
        <edmx:Include Namespace="com.sap.vocabularies.Common.v1" Alias="Common"/>
    </edmx:Reference>
    <edmx:Reference Uri="../../catalogservice;v=2/Vocabularies(TechnicalName='%2FIWBEP%2FVOC_UI',Version='0001',SAP__Origin='')/$value">
        <edmx:Include Namespace="com.sap.vocabularies.UI.v1" Alias="UI"/>
    </edmx:Reference>
    <edmx:Reference Uri="../../catalogservice;v=2/Vocabularies(TechnicalName='%2FIWBEP%2FVOC_COMMUNICATION',Version='0001',SAP__Origin='')/$value">
        <edmx:Include Namespace="com.sap.vocabularies.Communication.v1" Alias="Communication"/>
    </edmx:Reference>
    <edmx:Reference Uri="../../catalogservice;v=2/Vocabularies(TechnicalName='%2FIWBEP%2FVOC_PERSONALDATA',Version='0001',SAP__Origin='')/$value">
        <edmx:Include Namespace="com.sap.vocabularies.PersonalData.v1" Alias="PersonalData"/>
    </edmx:Reference>
    <edmx:Reference Uri="../../catalogservice;v=2/Vocabularies(TechnicalName='%2FIWBEP%2FVOC_VALIDATION',Version='0001',SAP__Origin='')/$value">
        <edmx:Include Namespace="Org.OData.Validation.V1" Alias="Validation"/>
    </edmx:Reference>
    <edmx:Reference Uri="../../catalogservice;v=2/Vocabularies(TechnicalName='%2FIWBEP%2FVOC_ANALYTICS',Version='0001',SAP__Origin='')/$value">
        <edmx:Include Namespace="com.sap.vocabularies.Analytics.v1" Alias="Analytics"/>
    </edmx:Reference>
    <edmx:Reference Uri="../../catalogservice;v=2/Vocabularies(TechnicalName='%2FIWBEP%2FVOC_HTML5',Version='0001',SAP__Origin='')/$value">
        <edmx:Include Namespace="com.sap.vocabularies.HTML5.v1" Alias="HTML5"/>
    </edmx:Reference>
    <edmx:Reference Uri="../../../sap/zsb_empmst/$metadata">
        <edmx:Include Namespace="ZSB_EMPMST" Alias="SAP"/>
    </edmx:Reference>
    <edmx:DataServices>
        <Schema Namespace="zsb_empmst_van.v1" xmlns="http://docs.oasis-open.org/odata/ns/edm">
            <Annotations Target="cds_zsd_empmst.Employee_masterType/Delete_mc">
                <Annotation Term="UI.Hidden"/>
            </Annotations>
            <Annotations Target="cds_zsd_empmst.Employee_masterType/Update_mc">
                <Annotation Term="UI.Hidden"/>
            </Annotations>
            <Annotations Target="cds_zsd_empmst.Employee_masterType">
                <Annotation Term="UI.Facets">
                    <Collection>
                        <Record Type="UI.ReferenceFacet">
                            <PropertyValue Property="Label" String="Employee master"/>
                            <PropertyValue Property="ID" String="Building"/>
                            <PropertyValue Property="Target" AnnotationPath="@UI.Identification"/>
                        </Record>
                    </Collection>
                </Annotation>
                <Annotation Term="UI.HeaderInfo">
                    <Record>
                        <PropertyValue Property="TypeName" String="Employee Master"/>
                        <PropertyValue Property="TypeNamePlural" String="Employee Masters"/>
                        <PropertyValue Property="TypeImageUrl" String="sap-icon://Empmst"/>
                        <PropertyValue Property="Title">
                            <Record Type="UI.DataField">
                                <PropertyValue Property="Value" Path="Empname"/>
                            </Record>
                        </PropertyValue>
                        <PropertyValue Property="Description">
                            <Record Type="UI.DataField">
                                <PropertyValue Property="Value" String="">
                                    <Annotation Term="Core.Messages">
                                        <Collection>
                                            <Record>
                                                <PropertyValue Property="code" String="SADL_GW_EXP_VOCAN-001"/>
                                                <PropertyValue Property="message" String="Property 'Empid' of annotation 'UI.HEADERINFO.DESCRIPTION' in proj./view 'Employee_master' not found"/>
                                                <PropertyValue Property="severity" String="error"/>
                                            </Record>
                                        </Collection>
                                    </Annotation>
                                </PropertyValue>
                            </Record>
                        </PropertyValue>
                    </Record>
                </Annotation>
                <Annotation Term="UI.Identification">
                    <Collection>
                        <Record Type="UI.DataField">
                            <PropertyValue Property="Value" Path="EmpId"/>
                        </Record>
                        <Record Type="UI.DataField">
                            <PropertyValue Property="Value" Path="Empname"/>
                        </Record>
                        <Record Type="UI.DataField">
                            <PropertyValue Property="Value" Path="Gender"/>
                        </Record>
                        <Record Type="UI.DataField">
                            <PropertyValue Property="Value" Path="Address"/>
                        </Record>
                        <Record Type="UI.DataField">
                            <PropertyValue Property="Value" Path="EmailId"/>
                        </Record>
                        <Record Type="UI.DataField">
                            <PropertyValue Property="Value" Path="MoNo"/>
                        </Record>
                    </Collection>
                </Annotation>
                <Annotation Term="UI.LineItem">
                    <Collection>
                        <Record Type="UI.DataField">
                            <PropertyValue Property="Value" Path="EmpId"/>
                        </Record>
                        <Record Type="UI.DataField">
                            <PropertyValue Property="Value" Path="Empname"/>
                        </Record>
                        <Record Type="UI.DataField">
                            <PropertyValue Property="Value" Path="Gender"/>
                        </Record>
                        <Record Type="UI.DataField">
                            <PropertyValue Property="Value" Path="Address"/>
                        </Record>
                        <Record Type="UI.DataField">
                            <PropertyValue Property="Value" Path="EmailId"/>
                        </Record>
                        <Record Type="UI.DataField">
                            <PropertyValue Property="Value" Path="MoNo"/>
                        </Record>
                    </Collection>
                </Annotation>
                <Annotation Term="UI.SelectionFields">
                    <Collection>
                        <PropertyPath>EmpId</PropertyPath>
                        <PropertyPath>Empname</PropertyPath>
                        <PropertyPath>Gender</PropertyPath>
                        <PropertyPath>Address</PropertyPath>
                        <PropertyPath>EmailId</PropertyPath>
                        <PropertyPath>MoNo</PropertyPath>
                    </Collection>
                </Annotation>
            </Annotations>
        </Schema>
    </edmx:DataServices>
</edmx:Edmx>